text_extractor/__init__.py
text_extractor/extractText.py
text_extra-0.1.4.dist-info/LICENSE
text_extra-0.1.4.dist-info/METADATA
text_extra-0.1.4.dist-info/WHEEL
text_extra-0.1.4.dist-info/top_level.txt
text_extra-0.1.4.dist-info/RECORD
