Metadata-Version: 2.1
Name: text-extra
Version: 0.1.4
Summary: A simple tool for text extraction from pdf, epub, txt, and docx files
Home-page: https://example.com/https://github.com/KirillAn/extractText/
Author: KirillAn
Author-email: kirillius.no@gmail.com
License: 
Project-URL: GitHub, https://github.com/KirillAn/extractText
Keywords: text extraction,pdf,epub,docx,txt
Classifier: Programming Language :: Python :: 3
Classifier: License :: OSI Approved :: GNU General Public License v3 or later (GPLv3+)
Classifier: Operating System :: OS Independent
Requires-Python: >=3.6
License-File: LICENSE
Requires-Dist: ebooklib
Requires-Dist: PyPDF2
Requires-Dist: beautifulsoup4
Requires-Dist: python-docx
Requires-Dist: pdfplumber >=0.5.24
Requires-Dist: Pillow >=7.0.0
Requires-Dist: pytesseract >=0.3.6
Requires-Dist: pdf2image >=1.14.0
Provides-Extra: dev
Requires-Dist: pytest >=3.7 ; extra == 'dev'
